mangadex_py/__init__.py
mangadex_py/__main__.py
mangadex_py/chapters.py
mangadex_py/download.py
mangadex_py/download_methods.py
mangadex_py/file_main.py
mangadex_py/fs.py
mangadex_py/http.py
mangadex_py/main.py
mangadex_py/manga.py
mangadex_py/meta.py
mangadex_py/naming.py
mangadex_py/report_health.py
mangadex_py/util.py
mangadex_py/auth/__init__.py
mangadex_py/auth/auth_actions.py
mangadex_py/auth/auth_fs.py
mangadex_py/auth/crypto.py
mangadex_py/cli/__init__.py
mangadex_py/cli/argparse.py
mangadex_py/cli/auth_args.py
mangadex_py/cli/downloading_args.py
mangadex_py/cli/general_args.py
mangadex_py/cli/required_args.py
Sydiepus_mangadex_py-1.410.dist-info/LICENSE
Sydiepus_mangadex_py-1.410.dist-info/METADATA
Sydiepus_mangadex_py-1.410.dist-info/WHEEL
Sydiepus_mangadex_py-1.410.dist-info/entry_points.txt
Sydiepus_mangadex_py-1.410.dist-info/top_level.txt
Sydiepus_mangadex_py-1.410.dist-info/RECORD
