Metadata-Version: 2.1
Name: Sydiepus-mangadex-py
Version: 1.410
Summary: MangaDexv5 manga downloader
Home-page: https://github.com/Sydiepus/mangadex-py
Author: Sydiepus
Author-email: sydiepus@gmail.com
License: MIT
Platform: any
Classifier: Development Status :: 5 - Production/Stable
Classifier: License :: OSI Approved :: MIT License
Classifier: Environment :: Console
Classifier: Programming Language :: Python :: 3.7
Classifier: Programming Language :: Python :: 3.8
Classifier: Programming Language :: Python :: 3.9
Classifier: Programming Language :: Python :: 3.10
Classifier: Operating System :: OS Independent
License-File: LICENSE
Requires-Dist: requests
Requires-Dist: tqdm
Requires-Dist: urllib3
